inquisitor/__init__.py
inquisitor-0.1.9.dist-info/DESCRIPTION.rst
inquisitor-0.1.9.dist-info/METADATA
inquisitor-0.1.9.dist-info/RECORD
inquisitor-0.1.9.dist-info/WHEEL
inquisitor-0.1.9.dist-info/metadata.json
inquisitor-0.1.9.dist-info/top_level.txt
tests/__init__.py
tests/mock.py
tests/test_api.py
