Metadata-Version: 2.0
Name: inquisitor
Version: 0.1.9
Summary: A Python client for econdb.com/api/
Home-page: https://github.com/inquirim/inquisitor
Author: Oriol Andres
Author-email: admin@econdb.com
License: MIT License
Download-URL: https://github.com/inquirim/inquisitor/tarball/0.1.9
Keywords: data,economics,finance,api
Platform: UNKNOWN
Classifier: Programming Language :: Python
Classifier: Development Status :: 4 - Beta
Classifier: License :: OSI Approved :: MIT License
Classifier: Operating System :: OS Independent
Classifier: Topic :: Software Development :: Libraries :: Python Modules
Classifier: Intended Audience :: Science/Research
Classifier: Topic :: Office/Business :: Financial :: Spreadsheet
Classifier: Programming Language :: Python :: 2.7
Classifier: Programming Language :: Python :: 3.4
Classifier: Programming Language :: Python :: 3.5
Requires-Dist: requests
Provides-Extra: pandas
Requires-Dist: pandas; extra == 'pandas'
